tests/__init__.py
tests/lib_test.py
wagon_tools/__init__.py
wagon_tools/lib.py
wagon_tools/data/README.rst
wagon_tools/data/data.csv
wagon_tools/data/skeleton/.gitignore
wagon_tools/data/skeleton/.gitlab-ci.yml
wagon_tools/data/skeleton/MANIFEST.in
wagon_tools/data/skeleton/Makefile
wagon_tools/data/skeleton/README.md
wagon_tools/data/skeleton/requirements.txt
wagon_tools/data/skeleton/setup.py
wagon_tools/data/skeleton/.github/workflows/pythonpackage.yml
wagon_tools/data/skeleton/proj/__init__.py
wagon_tools/data/skeleton/proj/lib.py
wagon_tools/data/skeleton/proj/data/data.csv.gz
wagon_tools/data/skeleton/scripts/proj-process
wagon_tools/data/skeleton/tests/__init__.py
wagon_tools/data/skeleton/tests/lib_test.py
wagon_tools-1.1.2.data/scripts/wagon-make-package
wagon_tools-1.1.2.dist-info/METADATA
wagon_tools-1.1.2.dist-info/WHEEL
wagon_tools-1.1.2.dist-info/top_level.txt
wagon_tools-1.1.2.dist-info/RECORD
