Metadata-Version: 2.1
Name: wagon-tools
Version: 1.1.2
Summary: Package builder with CI included
Home-page: https://github.com/lologibus2/wagon_tools
Author: Jean Bizot
Author-email: jea@gmail.com
License: UNKNOWN
Platform: UNKNOWN
